setup.py
fred/__init__.py
fred/api.py
fred/core.py
fred.egg-info/PKG-INFO
fred.egg-info/SOURCES.txt
fred.egg-info/dependency_links.txt
fred.egg-info/requires.txt
fred.egg-info/top_level.txt