Metadata-Version: 1.1
Name: fred
Version: 3.0
Summary: St. Louis Federal Reserve FRED API
Home-page: https://github.com/zachwill/fred
Author: Zach Williams
Author-email: hey@zachwill.com
License: MIT
Keywords: fred,fred api,federal reserve,st. louis fed
Platform: UNKNOWN
Classifier: Development Status :: 5 - Production/Stable
Classifier: Intended Audience :: Developers
Classifier: Natural Language :: English
Classifier: Operating System :: OS Independent
Classifier: Programming Language :: Python :: 2
Classifier: Programming Language :: Python :: 3
Classifier: Topic :: Internet
Classifier: Topic :: Internet :: WWW/HTTP
